sdwk/__init__.py
sdwk/cli.py
sdwk/commands/__init__.py
sdwk/commands/add.py
sdwk/commands/build.py
sdwk/commands/check.py
sdwk/commands/create.py
sdwk/commands/dev.py
sdwk/commands/export_flow.py
sdwk/commands/publish.py
sdwk/commands/remove.py
sdwk/config/default.yaml
sdwk/config/prompt.yaml
sdwk/config.py
sdwk/core/__init__.py
sdwk/core/artifact/__init__.py
sdwk/core/artifact/manager.py
sdwk/core/artifact/models.py
sdwk/core/artifact/storage.py
sdwk/core/component/__init__.py
sdwk/core/component/component.py
sdwk/core/component/data.py
sdwk/core/component/io.py
sdwk/core/component/types.py
sdwk/core/config_cache.py
sdwk/core/exceptions.py
sdwk/core/i18n/__init__.py
sdwk/core/i18n/decorators.py
sdwk/core/i18n/detector.py
sdwk/core/i18n/functions.py
sdwk/core/i18n/manager.py
sdwk/core/i18n/text.py
sdwk/core/llm/__init__.py
sdwk/core/llm/llm_manager.py
sdwk/core/llm/llm_service.py
sdwk/core/logging/__init__.py
sdwk/core/logging/config.py
sdwk/core/logging/log_publisher.py
sdwk/core/logging/logger_adapter.py
sdwk/core/logging/loguru_handler.py
sdwk/core/platform_client/__init__.py
sdwk/core/platform_client/base.py
sdwk/core/platform_client/client.py
sdwk/core/project_config.py
sdwk/core/project_settings.py
sdwk/core/template_manager.py
sdwk/locales/en.json
sdwk/locales/zh-CN.json
sdwk/py.typed
sdwk/templates/graph/.gitignore
sdwk/templates/graph/.pre-commit-config.yaml
sdwk/templates/graph/.python-version
sdwk/templates/graph/COMPONENT_GUIDE.md
sdwk/templates/graph/README.md
sdwk/templates/graph/config/settings.yaml
sdwk/templates/graph/pyproject.toml
sdwk/templates/graph/sdw.json
sdwk/templates/graph/src/__init__.py
sdwk/templates/graph/src/examples.py
sdwk/templates/graph/src/graph.py
sdwk/templates/graph/src/main.py
sdwk/templates/graph/src/models.py
sdwk/templates/graph/src/nodes/__init__.py
sdwk/templates/graph/src/nodes/adapter.py
sdwk/templates/graph/src/nodes/base.py
sdwk/templates/graph/src/nodes/components.py
sdwk/templates/graph/src/nodes/custom.py
sdwk-0.1.9.dist-info/WHEEL
sdwk-0.1.9.dist-info/entry_points.txt
sdwk-0.1.9.dist-info/METADATA
sdwk-0.1.9.dist-info/RECORD
