Metadata-Version: 2.3
Name: sdwk
Version: 0.1.9
Summary: SDW Platform SDK
Author: 徐侨
Author-email: 徐侨 <xu.qiao@kotei.com.cn>
Requires-Dist: click>=8.0.0
Requires-Dist: rich>=13.0.0
Requires-Dist: questionary>=2.0.0
Requires-Dist: jinja2>=3.0.0
Requires-Dist: pydantic>=2.0.0
Requires-Dist: httpx>=0.25.0
Requires-Dist: dynaconf>=3.2.12
Requires-Dist: loguru>=0.7.0
Requires-Dist: pika>=1.3.0
Requires-Dist: pyyaml>=6.0.0
Requires-Dist: pathspec>=0.11.0
Requires-Dist: pyarrow>=22.0.0
Requires-Dist: pandas>=2.3.3
Requires-Dist: langchain-openai>=1.1.6
Requires-Dist: openai>=2.14.0
Requires-Python: >=3.10
